<?xml version="1.0" encoding="UTF-8"?><record_update sys_domain="global" table="sys_ux_page_property">
    <sys_ux_page_property action="DELETE">
        <choices/>
        <description/>
        <name>chrome_header</name>
        <page display_value="citibank">af9bc76683b09210e456bed6feaad3e9</page>
        <required_translations>[ ]</required_translations>
        <route/>
        <suffix/>
        <sys_class_name>sys_ux_page_property</sys_class_name>
        <sys_created_by>admin</sys_created_by>
        <sys_created_on>2024-09-25 16:40:28</sys_created_on>
        <sys_domain>global</sys_domain>
        <sys_domain_path>global</sys_domain_path>
        <sys_id>51ab0b6683b09210e456bed6feaad37e</sys_id>
        <sys_mod_count>0</sys_mod_count>
        <sys_name>chrome_header</sys_name>
        <sys_package display_value="NeedIt" source="x_58872_needit">6ead8e780f603200cd674f8ce1050ed1</sys_package>
        <sys_policy/>
        <sys_scope display_value="NeedIt">6ead8e780f603200cd674f8ce1050ed1</sys_scope>
        <sys_update_name>sys_ux_page_property_51ab0b6683b09210e456bed6feaad37e</sys_update_name>
        <sys_updated_by>admin</sys_updated_by>
        <sys_updated_on>2024-09-25 16:40:28</sys_updated_on>
        <type>json</type>
        <unique_name>x_58872_needit.af9bc76683b09210e456bed6feaad3e9.root.chrome_header</unique_name>
        <value>{"privatePage":{"userPrefsEnabled":false,"searchEnabled":false,"currentScreenLinkConfiguration":{},"globalTools":{"collapsingMenuId":0,"primaryItems":[],"secondaryItems":[]}},"publicPage":{"menuEnabled":false,"searchEnabled":false,"logoRoute":{},"actionButtons":[]}}</value>
    </sys_ux_page_property>
    <sys_translated_text action="DELETE" query="documentkey=51ab0b6683b09210e456bed6feaad37e"/>
    <sys_update_version action="INSERT_OR_UPDATE">
        <action>DELETE</action>
        <application display_value="NeedIt">6ead8e780f603200cd674f8ce1050ed1</application>
        <file_path/>
        <instance_id>871156c6dbf1715438f1172913961991</instance_id>
        <instance_name>dev183489</instance_name>
        <name>sys_ux_page_property_51ab0b6683b09210e456bed6feaad37e</name>
        <payload><![CDATA[<?xml version="1.0" encoding="UTF-8"?><record_update sys_domain="global" table="sys_ux_page_property"><sys_ux_page_property action="INSERT_OR_UPDATE"><choices/><description/><name>chrome_header</name><page display_value="citibank">af9bc76683b09210e456bed6feaad3e9</page><required_translations>[ ]</required_translations><route/><suffix/><sys_class_name>sys_ux_page_property</sys_class_name><sys_created_by>admin</sys_created_by><sys_created_on>2024-09-25 16:40:28</sys_created_on><sys_domain>global</sys_domain><sys_domain_path>global</sys_domain_path><sys_id>51ab0b6683b09210e456bed6feaad37e</sys_id><sys_mod_count>0</sys_mod_count><sys_name>chrome_header</sys_name><sys_package display_value="NeedIt" source="x_58872_needit">6ead8e780f603200cd674f8ce1050ed1</sys_package><sys_policy/><sys_scope display_value="NeedIt">6ead8e780f603200cd674f8ce1050ed1</sys_scope><sys_update_name>sys_ux_page_property_51ab0b6683b09210e456bed6feaad37e</sys_update_name><sys_updated_by>admin</sys_updated_by><sys_updated_on>2024-09-25 16:40:28</sys_updated_on><type>json</type><unique_name>x_58872_needit.af9bc76683b09210e456bed6feaad3e9.root.chrome_header</unique_name><value>{"privatePage":{"userPrefsEnabled":false,"searchEnabled":false,"currentScreenLinkConfiguration":{},"globalTools":{"collapsingMenuId":0,"primaryItems":[],"secondaryItems":[]}},"publicPage":{"menuEnabled":false,"searchEnabled":false,"logoRoute":{},"actionButtons":[]}}</value></sys_ux_page_property><sys_translated_text action="delete_multiple" query="documentkey=51ab0b6683b09210e456bed6feaad37e"/></record_update>]]></payload>
        <payload_hash>-56899650</payload_hash>
        <record_name>chrome_header</record_name>
        <reverted_from/>
        <source>a543283783c49210e456bed6feaad397</source>
        <source_table>sys_update_set</source_table>
        <state>previous</state>
        <sys_created_by>admin</sys_created_by>
        <sys_created_on>2024-09-25 16:40:28</sys_created_on>
        <sys_id>99ab0b6683b09210e456bed6feaad380</sys_id>
        <sys_mod_count>0</sys_mod_count>
        <sys_recorded_at>1922a0e3aa90000001</sys_recorded_at>
        <sys_updated_by>admin</sys_updated_by>
        <sys_updated_on>2024-09-25 16:40:28</sys_updated_on>
        <type>UX Page Property</type>
        <update_guid>ddab0b66ecb0921003e16b499a4bd27f</update_guid>
        <update_guid_history>ddab0b66ecb0921003e16b499a4bd27f:-56899650</update_guid_history>
    </sys_update_version>
    <sys_metadata_delete action="INSERT_OR_UPDATE">
        <sys_audit_delete/>
        <sys_class_name>sys_metadata_delete</sys_class_name>
        <sys_created_by>admin</sys_created_by>
        <sys_created_on>2024-09-25 16:44:02</sys_created_on>
        <sys_db_object display_value="" name="sys_ux_page_property">sys_ux_page_property</sys_db_object>
        <sys_id>5f88bc6d39f04b58be66cb8275bfd751</sys_id>
        <sys_metadata>51ab0b6683b09210e456bed6feaad37e</sys_metadata>
        <sys_mod_count>0</sys_mod_count>
        <sys_name>chrome_header</sys_name>
        <sys_package display_value="NeedIt" source="x_58872_needit">6ead8e780f603200cd674f8ce1050ed1</sys_package>
        <sys_parent/>
        <sys_policy/>
        <sys_scope display_value="NeedIt">6ead8e780f603200cd674f8ce1050ed1</sys_scope>
        <sys_scope_delete display_value="">94872a8897db403e8ee69a431de2fca4</sys_scope_delete>
        <sys_update_name>sys_ux_page_property_51ab0b6683b09210e456bed6feaad37e</sys_update_name>
        <sys_update_version display_value="sys_ux_page_property_51ab0b6683b09210e456bed6feaad37e">99ab0b6683b09210e456bed6feaad380</sys_update_version>
        <sys_updated_by>admin</sys_updated_by>
        <sys_updated_on>2024-09-25 16:44:02</sys_updated_on>
    </sys_metadata_delete>
</record_update>
